pybec/.DS_Store
pybec/__init__.py
pybec/_version.py
pybec/analysis.py
pybec/output.py
pybec/parsers.py
pybec/plotters.py
pybec/utils.py
pybec/data/README.md
pybec/data/look_and_say.dat
pybec/tests/__init__.py
pybec/tests/test_pybec.py
pybec-0.1.2.dist-info/LICENSE
pybec-0.1.2.dist-info/METADATA
pybec-0.1.2.dist-info/WHEEL
pybec-0.1.2.dist-info/top_level.txt
pybec-0.1.2.dist-info/RECORD
