Metadata-Version: 2.1
Name: pybec
Version: 0.1.2
Summary: UNKNOWN
Home-page: https://pybec.readthedocs.io/en/latest/
Author: Brett Henderson
Author-email: brettrhenderson25@gmail.com
License: MIT
Platform: Linux
Platform: Mac OS-X
Platform: Unix
Platform: Windows
Requires-Python: >=3.5
Requires-Dist: toolz (>=0.8.2)
Requires-Dist: dask (>=1.2.2)
Requires-Dist: matplotlib (>=3.0.3)
Requires-Dist: numpy (>=1.16.2)
Requires-Dist: pandas (>=0.24.2)
Requires-Dist: scipy (>=1.2.1)
Requires-Dist: sklearn
Requires-Dist: pykrige
